{
  "title": "00 - Cluster Operations",
  "description": "Use cluster commands",
  "details": {
    "intro": {
      "text": "intro.md"
    },
    "steps": [
      {
        "title": "Cluster Info",
        "text": "step1.md"
      },
      {
        "title": "Show cluster nodes",
        "text": "step2.md"
      },
      {
        "title": "Cluster configuration",
        "text": "step3.md"
      },
      {
        "title": "Namespaces",
        "text": "step4.md"
      }
    ],
    "finish": {
      "text": "finish.md"
    }
  },
  "backend": {
    "imageid": "kubernetes-kubeadm-2nodes"
  }
}
